{
  "metadata" : {
    "realm" : "/",
    "entityType" : "PasswordCollectorNode",
    "entityId" : "default/ce4d4634-1ad7-4488-81ae-e22f3ce35969",
    "uid" : "ou=ce4d4634-1ad7-4488-81ae-e22f3ce35969,ou=default,ou=OrganizationConfig,ou=1.0,ou=PasswordCollectorNode,ou=services,ou=am-config",
    "sunServiceID" : "instance",
    "objectClass" : [ "top", "sunServiceComponent" ],
    "pathParams" : { },
    "ou" : null
  },
  "data" : {
    "_id" : "default/ce4d4634-1ad7-4488-81ae-e22f3ce35969",
    "_type" : {
      "_id" : "PasswordCollectorNode",
      "name" : "PasswordCollectorNode",
      "collection" : false
    }
  }
}